AI_WQ_package/__init__.py
AI_WQ_package/check_fc_submission.py
AI_WQ_package/compute_20yr_quintile_climatology.py
AI_WQ_package/download_ERA5_training_data.py
AI_WQ_package/forecast_evaluation.py
AI_WQ_package/forecast_submission.py
AI_WQ_package/plotting_forecast.py
AI_WQ_package/retrieve_evaluation_data.py
AI_WQ_package/retrieve_training_data.py
ai_wq_package-3.0.3.dist-info/licenses/LICENSE
ai_wq_package-3.0.3.dist-info/METADATA
ai_wq_package-3.0.3.dist-info/WHEEL
ai_wq_package-3.0.3.dist-info/top_level.txt
ai_wq_package-3.0.3.dist-info/RECORD
