Metadata-Version: 2.4
Name: AI_WQ_package
Version: 3.0.3
Summary: A python package to support forecast submission, evaluation and access to FTP site for DESTIN-E S2S AI prediction project
Author-email: Joshua Talib <joshuatalib@ecmwf.int>
Project-URL: Homepage, https://github.com/joshuatalib/AI_weather_quest
Classifier: Programming Language :: Python :: 3
Classifier: License :: OSI Approved :: MIT License
Classifier: Operating System :: OS Independent
Requires-Python: >=3.8
License-File: LICENSE
Requires-Dist: numpy>=1.23
Requires-Dist: xarray>=2024.09.0
Requires-Dist: dask>=2024.9.0
Requires-Dist: pandas>=2.2.3
Requires-Dist: scipy>=1.14.1
Requires-Dist: netCDF4>=1.7.2
Requires-Dist: requests>=2.32.2
Requires-Dist: matplotlib>=3.8
Requires-Dist: cartopy>=0.22
Dynamic: license-file
